{
  "main": {
    "id": "1808d3c068d78d39",
    "type": "split",
    "children": [
      {
        "id": "d95dee4a941796a3",
        "type": "tabs",
        "children": [
          {
            "id": "4a63826d8763a52f",
            "type": "leaf",
            "state": {
              "type": "markdown",
              "state": {
                "file": "2023-10-15.md",
                "mode": "source",
                "source": true
              }
            }
          },
          {
            "id": "58233b9479f4c517",
            "type": "leaf",
            "state": {
              "type": "markdown",
              "state": {
                "file": "0-閃念筆記/DEMO附件.md",
                "mode": "source",
                "source": true
              }
            }
          }
        ],
        "currentTab": 1
      }
    ],
    "direction": "vertical"
  },
  "left": {
    "id": "37e5a097fe25699c",
    "type": "split",
    "children": [
      {
        "id": "1d2574cad37e9aac",
        "type": "tabs",
        "children": [
          {
            "id": "35bca3006b06b72b",
            "type": "leaf",
            "state": {
              "type": "file-explorer",
              "state": {
                "sortOrder": "alphabetical"
              }
            }
          },
          {
            "id": "248997b5e20021ef",
            "type": "leaf",
            "state": {
              "type": "search",
              "state": {
                "query": "",
                "matchingCase": false,
                "explainSearch": false,
                "collapseAll": false,
                "extraContext": false,
                "sortOrder": "alphabetical"
              }
            }
          },
          {
            "id": "46843ebf2eaeed13",
            "type": "leaf",
            "state": {
              "type": "bookmarks",
              "state": {}
            }
          }
        ]
      }
    ],
    "direction": "horizontal",
    "width": 300
  },
  "right": {
    "id": "92792dbe9e0f5758",
    "type": "split",
    "children": [
      {
        "id": "4ef6c4530058c310",
        "type": "tabs",
        "children": [
          {
            "id": "3268568ec9e590f4",
            "type": "leaf",
            "state": {
              "type": "backlink",
              "state": {
                "file": "2023-10-15.md",
                "collapseAll": false,
                "extraContext": false,
                "sortOrder": "alphabetical",
                "showSearch": false,
                "searchQuery": "",
                "backlinkCollapsed": false,
                "unlinkedCollapsed": true
              }
            }
          },
          {
            "id": "1e3b813ee753ef0c",
            "type": "leaf",
            "state": {
              "type": "outgoing-link",
              "state": {
                "file": "2023-10-15.md",
                "linksCollapsed": false,
                "unlinkedCollapsed": true
              }
            }
          },
          {
            "id": "2762473b915fe83a",
            "type": "leaf",
            "state": {
              "type": "tag",
              "state": {
                "sortOrder": "frequency",
                "useHierarchy": true
              }
            }
          },
          {
            "id": "82f7449ab38793e1",
            "type": "leaf",
            "state": {
              "type": "outline",
              "state": {
                "file": "2023-10-15.md"
              }
            }
          }
        ]
      }
    ],
    "direction": "horizontal",
    "width": 300,
    "collapsed": true
  },
  "left-ribbon": {
    "hiddenItems": {
      "table-editor-obsidian:Advanced Tables Toolbar": false,
      "switcher:開啟快速切換": false,
      "graph:查看關聯圖": false,
      "canvas:建立新畫布": false,
      "daily-notes:開啟今天的每日筆記": false,
      "templates:插入模板": false,
      "command-palette:開啟命令面板": false
    }
  },
  "active": "35bca3006b06b72b",
  "lastOpenFiles": [
    "0-閃念筆記/attachments/樓雨晴-綺情之尋覓篇-重生.pdf",
    "0-閃念筆記/attachments",
    "樓雨晴-綺情之尋覓篇-重生.pdf",
    "2023-10-15.md",
    "0-閃念筆記/DEMO附件.md",
    "未命名",
    "Z-樣板",
    "X-主題索引",
    "4-生產力",
    "3-投資理財",
    "2-文獻筆記",
    "0-閃念筆記",
    "1-日誌/esharp筆記.md",
    "1-日誌"
  ]
}